README.md
setup.py
saithonanen/__init__.py
saithonanen/api.py
saithonanen/asymmetric.py
saithonanen/cli.py
saithonanen/quantum_resistant.py
saithonanen/security.py
saithonanen/symmetric.py
saithonanen.egg-info/PKG-INFO
saithonanen.egg-info/SOURCES.txt
saithonanen.egg-info/dependency_links.txt
saithonanen.egg-info/entry_points.txt
saithonanen.egg-info/requires.txt
saithonanen.egg-info/top_level.txt