Metadata-Version: 2.1
Name: saithonanen
Version: 0.1.0
Summary: A powerful and advanced encryption library.
Home-page: https://github.com/your-username/saithonanen
Author: Manus AI
Author-email: 
License: UNKNOWN
Platform: UNKNOWN
